odoo/addons/mrp_bom_widget_section_and_note_one2many/README.rst
odoo/addons/mrp_bom_widget_section_and_note_one2many/__init__.py
odoo/addons/mrp_bom_widget_section_and_note_one2many/__manifest__.py
odoo/addons/mrp_bom_widget_section_and_note_one2many/i18n/fr.po
odoo/addons/mrp_bom_widget_section_and_note_one2many/i18n/it.po
odoo/addons/mrp_bom_widget_section_and_note_one2many/i18n/mrp_bom_widget_section_and_note_one2many.pot
odoo/addons/mrp_bom_widget_section_and_note_one2many/i18n/pt_BR.po
odoo/addons/mrp_bom_widget_section_and_note_one2many/models/__init__.py
odoo/addons/mrp_bom_widget_section_and_note_one2many/models/mrp_bom.py
odoo/addons/mrp_bom_widget_section_and_note_one2many/models/mrp_bom_line.py
odoo/addons/mrp_bom_widget_section_and_note_one2many/readme/CONTRIBUTORS.md
odoo/addons/mrp_bom_widget_section_and_note_one2many/readme/CREDITS.md
odoo/addons/mrp_bom_widget_section_and_note_one2many/readme/DESCRIPTION.md
odoo/addons/mrp_bom_widget_section_and_note_one2many/readme/ROADMAP.md
odoo/addons/mrp_bom_widget_section_and_note_one2many/readme/USAGE.md
odoo/addons/mrp_bom_widget_section_and_note_one2many/static/description/icon.png
odoo/addons/mrp_bom_widget_section_and_note_one2many/static/description/index.html
odoo/addons/mrp_bom_widget_section_and_note_one2many/static/description/mrp_bom_widget_add_section_and_note.gif
odoo/addons/mrp_bom_widget_section_and_note_one2many/views/view_mrp_bom.xml
odoo_addon_mrp_bom_widget_section_and_note_one2many-18.0.1.0.0.4.dist-info/METADATA
odoo_addon_mrp_bom_widget_section_and_note_one2many-18.0.1.0.0.4.dist-info/WHEEL
odoo_addon_mrp_bom_widget_section_and_note_one2many-18.0.1.0.0.4.dist-info/top_level.txt
odoo_addon_mrp_bom_widget_section_and_note_one2many-18.0.1.0.0.4.dist-info/RECORD
