Metadata-Version: 2.1
Name: odoo-addon-mrp_bom_widget_section_and_note_one2many
Version: 18.0.1.0.0.4
Requires-Python: >=3.10
Requires-Dist: odoo==18.0.*
Summary: Add section and note in Bills of Materials
Home-page: https://github.com/OCA/manufacture
License: AGPL-3
Author: GRAP,Odoo Community Association (OCA)
Author-email: support@odoo-community.org
Classifier: Programming Language :: Python
Classifier: Framework :: Odoo
Classifier: Framework :: Odoo :: 18.0
Classifier: License :: OSI Approved :: GNU Affero General Public License v3
